chippymu/__init__.py
chippymu/channelgen.py
chippymu/configs.py
chippymu/models.py
chippymu/sound.py
chippymu/utils.py
chippymu-0.4.0.dist-info/METADATA
chippymu-0.4.0.dist-info/WHEEL
chippymu-0.4.0.dist-info/entry_points.txt
chippymu-0.4.0.dist-info/RECORD
