Metadata-Version: 2.4
Name: chippymu
Version: 0.4.0
Summary: 一个用numpy实现的8bit音乐生成器
Author-email: wolido <270262953@qq.com>
Requires-Python: >=3.13
Requires-Dist: numpy>=2.3.0
Requires-Dist: sounddevice>=0.5.2
